Metadata-Version: 2.1
Name: cruds-dj-adminlte2
Version: 1.0
Summary: cruds_dj_adminlte2 is simple drop-in django app that creates CRUD for faster prototyping.
Home-page: https://github.com/TralahM/cruds_dj_adminlte2
Author: Tralah M. Brian
Author-email: briantralah@gmail.com
License: BSD
Keywords: django-cruds-adminlte
Platform: UNKNOWN
Classifier: Development Status :: 2 - Pre-Alpha
Classifier: Framework :: Django
Classifier: Intended Audience :: Developers
Classifier: License :: OSI Approved :: BSD License
Classifier: Natural Language :: English
Classifier: Programming Language :: Python :: 3
Classifier: Programming Language :: Python :: 3.7
Requires-Dist: django (>=2.2)
Requires-Dist: django-crispy-forms (==1.7.2)
Requires-Dist: djangoajax (==2.3.7)
